brain/__init__.py
brain/_version.py
brain/core/Cortex.py
brain/core/HookManager.py
brain/core/NeuronExceptions.py
brain/core/NeuronLauncher.py
brain/core/NeuronModule.py
brain/core/NeuronParameterLoader.py
brain/core/NotificationManager.py
brain/core/OrderAnalyser.py
brain/core/OrderListener.py
brain/core/PlayerLauncher.py
brain/core/PlayerModule.py
brain/core/ResourcesManager.py
brain/core/SignalLauncher.py
brain/core/SignalModule.py
brain/core/SynapseLauncher.py
brain/core/TriggerLauncher.py
brain/core/__init__.py
brain/core/ConfigurationManager/BrainLoader.py
brain/core/ConfigurationManager/ConfigurationChecker.py
brain/core/ConfigurationManager/DnaLoader.py
brain/core/ConfigurationManager/SettingEditor.py
brain/core/ConfigurationManager/SettingLoader.py
brain/core/ConfigurationManager/YAMLLoader.py
brain/core/ConfigurationManager/__init__.py
brain/core/Lifo/LIFOBuffer.py
brain/core/Lifo/LifoManager.py
brain/core/Lifo/__init__.py
brain/core/Models/APIResponse.py
brain/core/Models/Brain.py
brain/core/Models/Dna.py
brain/core/Models/MatchedSynapse.py
brain/core/Models/Neuron.py
brain/core/Models/Signal.py
brain/core/Models/Singleton.py
brain/core/Models/Synapse.py
brain/core/Models/__init__.py
brain/core/Models/settings/Options.py
brain/core/Models/settings/Player.py
brain/core/Models/settings/Resources.py
brain/core/Models/settings/RestAPI.py
brain/core/Models/settings/Settings.py
brain/core/Models/settings/SettingsEntry.py
brain/core/Models/settings/Stt.py
brain/core/Models/settings/Trigger.py
brain/core/Models/settings/Tts.py
brain/core/Models/settings/__init__.py
brain/core/RestAPI/FlaskAPI.py
brain/core/RestAPI/__init__.py
brain/core/RestAPI/utils.py
brain/core/TTS/TTSModule.py
brain/core/TTS/__init__.py
brain/core/Utils/FileManager.py
brain/core/Utils/Utils.py
brain/core/Utils/__init__.py
brain/neurons/__init__.py
brain/neurons/ansible_playbook/__init__.py
brain_ai-0.1.5.dist-info/METADATA
brain_ai-0.1.5.dist-info/RECORD
brain_ai-0.1.5.dist-info/WHEEL
brain_ai-0.1.5.dist-info/entry_points.txt
brain_ai-0.1.5.dist-info/top_level.txt
